_ReST/Directives.py
_ReST/HTML_Writer.py
_ReST/LICENSE
_ReST/README.rst
_ReST/Roles.py
_ReST/To_Html.py
_ReST/VERSION.py
_ReST/__init__.py
_ReST/babel.cfg
_ReST/setup.cfg
_ReST/setup.py
_ReST/-I18N/de.po
_ReST/-I18N/en.po
_ReST/-I18N/pt.po
_ReST/-I18N/template.pot
ReST_Tapyr-3.9.dist-info/LICENSE
ReST_Tapyr-3.9.dist-info/METADATA
ReST_Tapyr-3.9.dist-info/WHEEL
ReST_Tapyr-3.9.dist-info/top_level.txt
ReST_Tapyr-3.9.dist-info/RECORD
